pyvisa_py/__init__.py
pyvisa_py/attributes.py
pyvisa_py/common.py
pyvisa_py/gpib.py
pyvisa_py/highlevel.py
pyvisa_py/serial.py
pyvisa_py/sessions.py
pyvisa_py/tcpip.py
pyvisa_py/usb.py
pyvisa_py/version.py
pyvisa_py/protocols/__init__.py
pyvisa_py/protocols/hislip.py
pyvisa_py/protocols/rpc.py
pyvisa_py/protocols/usbraw.py
pyvisa_py/protocols/usbtmc.py
pyvisa_py/protocols/usbutil.py
pyvisa_py/protocols/vxi11.py
pyvisa_py/protocols/xdrlib.py
pyvisa_py/testsuite/__init__.py
pyvisa_py/testsuite/test_common.py
pyvisa_py/testsuite/test_highlevel.py
pyvisa_py/testsuite/test_serial.py
pyvisa_py/testsuite/test_sessions.py
pyvisa_py/testsuite/keysight_assisted_tests/__init__.py
pyvisa_py/testsuite/keysight_assisted_tests/test_resource_manager.py
pyvisa_py/testsuite/keysight_assisted_tests/test_tcpip_resources.py
PyVISA_py-0.7.2.dist-info/AUTHORS
PyVISA_py-0.7.2.dist-info/LICENSE
PyVISA_py-0.7.2.dist-info/METADATA
PyVISA_py-0.7.2.dist-info/WHEEL
PyVISA_py-0.7.2.dist-info/top_level.txt
PyVISA_py-0.7.2.dist-info/RECORD
