Metadata-Version: 2.1
Name: PyVISA-py
Version: 0.7.2
Summary: Pure Python implementation of a VISA library.
Author-email: "Hernan E. Grecco" <hernan.grecco@gmail.com>
Maintainer-email: "Matthieu C. Dartiailh" <m.dartiailh@gmail.com>
License: The MIT License
Project-URL: homepage, https://github.com/pyvisa/pyvisa-py
Project-URL: documentation, https://pyvisa-py.readthedocs.io/en/latest/
Project-URL: repository, https://github.com/pyvisa/pyvisa-py
Project-URL: changelog, https://github.com/pyvisa/pyvisa-py/blob/main/CHANGES
Keywords: VISA,GPIB,USB,serial,RS232,measurement,acquisition
Classifier: Development Status :: 4 - Beta
Classifier: Intended Audience :: Developers
Classifier: Intended Audience :: Science/Research
Classifier: License :: OSI Approved :: MIT License
Classifier: Operating System :: Microsoft :: Windows
Classifier: Operating System :: POSIX :: Linux
Classifier: Operating System :: MacOS :: MacOS X
Classifier: Programming Language :: Python
Classifier: Topic :: Scientific/Engineering :: Interface Engine/Protocol Translator
Classifier: Topic :: Software Development :: Libraries :: Python Modules
Classifier: Programming Language :: Python :: 3.8
Classifier: Programming Language :: Python :: 3.9
Classifier: Programming Language :: Python :: 3.10
Classifier: Programming Language :: Python :: 3.11
Classifier: Programming Language :: Python :: 3.12
Requires-Python: >=3.8
License-File: LICENSE
License-File: AUTHORS
Requires-Dist: pyvisa>=1.13.0
Requires-Dist: typing_extensions
Provides-Extra: gpib-ctypes
Requires-Dist: gpib-ctypes>=0.3.0; extra == "gpib-ctypes"
Provides-Extra: serial
Requires-Dist: pyserial>=3.0; extra == "serial"
Provides-Extra: usb
Requires-Dist: pyusb; extra == "usb"
Provides-Extra: psutil
Requires-Dist: psutil; extra == "psutil"
Provides-Extra: hislip-discovery
Requires-Dist: zeroconf; extra == "hislip-discovery"
Provides-Extra: vicp
Requires-Dist: pyvicp; extra == "vicp"
Requires-Dist: zeroconf; extra == "vicp"
